LICENSE
MANIFEST.in
README.md
VERSION
main.py
setup.py
tkinterutils.py
views.py
views_trading.py
catan_spectator.egg-info/PKG-INFO
catan_spectator.egg-info/SOURCES.txt
catan_spectator.egg-info/dependency_links.txt
catan_spectator.egg-info/entry_points.txt
catan_spectator.egg-info/requires.txt
catan_spectator.egg-info/top_level.txt