Metadata-Version: 1.1
Name: catan-spectator
Version: 0.1.4
Summary: Transcribe games of Settlers of Catan for research purposes, replay purposes, broadcast purposes, etc.
Home-page: https://github.com/rosshamish/catan-spectator/
Author: Ross Anderson
Author-email: ross.anderson@ualberta.ca
License: GPLv3
Download-URL: https://github.com/rosshamish/catan-spectator/tarball/0.1.4
